nimbus_twitter/__init__.py
nimbus_twitter/main.py.py
nimbus_twitter-0.0.1.dist-info/METADATA
nimbus_twitter-0.0.1.dist-info/WHEEL
nimbus_twitter-0.0.1.dist-info/top_level.txt
nimbus_twitter-0.0.1.dist-info/RECORD
