Metadata-Version: 2.1
Name: nimbus-twitter
Version: 0.0.1
Summary: Twitter Only Here
Author: nimbusnext (Atharv Patawar)
Author-email: <mail@neuralnine.com>
Keywords: python,twitter,scrape
Classifier: Development Status :: 1 - Planning
Classifier: Intended Audience :: Developers
Classifier: Programming Language :: Python :: 3
Classifier: Operating System :: Unix
Classifier: Operating System :: MacOS :: MacOS X
Classifier: Operating System :: Microsoft :: Windows
Requires-Dist: snscrape
Requires-Dist: pandas
